node.py
trie.py
trie_double.py
mih_trie-1.2.9.dist-info/METADATA
mih_trie-1.2.9.dist-info/WHEEL
mih_trie-1.2.9.dist-info/namespace_packages.txt
mih_trie-1.2.9.dist-info/top_level.txt
mih_trie-1.2.9.dist-info/zip-safe
mih_trie-1.2.9.dist-info/RECORD
