Metadata-Version: 2.1
Name: mih-trie
Version: 1.2.9
Summary: UNKNOWN
Home-page: UNKNOWN
Author: MIH
Author-email: UNKNOWN
License: UNKNOWN
Platform: UNKNOWN
Classifier: Development Status :: 3 - Alpha
Classifier: Programming Language :: Python
Requires-Dist: mih-sort (==0.4.6)
